app/__init__.py
app/asgi.py
app/cli.py
app/domain/__init__.py
app/domain/calculator/__init__.py
app/domain/calculator/controllers/__init__.py
app/domain/calculator/controllers/calculator.py
app/domain/calculator/schema.py
app/domain/system/__init__.py
app/domain/system/controllers/__init__.py
app/domain/system/controllers/system.py
app/domain/urls.py
app/domain/web/__init__.py
app/domain/web/controllers/__init__.py
app/domain/web/controllers/web.py
app/domain/web/resources/badge.png
app/domain/web/resources/input.css
app/domain/web/resources/logo.svg
app/domain/web/resources/style.css
app/domain/web/resources/tailwind/_base.css
app/domain/web/resources/tailwind/_components.css
app/domain/web/resources/tailwind/_utilities.css
app/domain/web/templates/base/base.html
app/domain/web/templates/base/footer.html
app/domain/web/templates/base/nav.html
app/domain/web/templates/index.html
app/domain/web/templates/partial.html
app/lib/__init__.py
app/lib/cors.py
app/lib/exceptions.py
app/lib/log/__init__.py
app/lib/log/controller.py
app/lib/log/utils.py
app/lib/openapi.py
app/lib/schema.py
app/lib/serialization.py
app/lib/settings.py
app/lib/static_files.py
app/lib/template.py
app/metadata.py
app/py.typed
app/utils.py
niapi-0.5.0.dist-info/LICENSE
niapi-0.5.0.dist-info/METADATA
niapi-0.5.0.dist-info/WHEEL
niapi-0.5.0.dist-info/entry_points.txt
niapi-0.5.0.dist-info/RECORD
