Metadata-Version: 2.1
Name: niapi
Version: 0.5.0
Summary: Network Data API
Home-page: https://github.com/JacobCoffee/niapi
License: MIT
Keywords: niapi,network,api,tool,rest,http,asgi,pydantic,litestar,starlite,websocket
Author: Jacob Coffee
Author-email: jacob@z7x.org
Maintainer: Jacob Coffee
Maintainer-email: jacob@z7x.org
Requires-Python: >=3.11,<4.0
Classifier: Development Status :: 3 - Alpha
Classifier: Environment :: Web Environment
Classifier: Framework :: AsyncIO
Classifier: Framework :: Pydantic
Classifier: Framework :: Pydantic :: 1
Classifier: Intended Audience :: Developers
Classifier: Intended Audience :: Information Technology
Classifier: Intended Audience :: System Administrators
Classifier: License :: OSI Approved :: MIT License
Classifier: Natural Language :: English
Classifier: Operating System :: OS Independent
Classifier: Programming Language :: Python
Classifier: Programming Language :: Python :: 3
Classifier: Programming Language :: Python :: 3.11
Classifier: Programming Language :: Python :: 3.12
Classifier: Topic :: Internet
Classifier: Topic :: Internet :: WWW/HTTP
Classifier: Topic :: Software Development
Classifier: Topic :: System :: Networking
Classifier: Typing :: Typed
Requires-Dist: litestar[prometheus,standard,structlog] (==2.0b2)
Requires-Dist: poetry (>=1.5.1,<2.0.0)
Requires-Dist: python-dotenv (>=1.0.0,<2.0.0)
Project-URL: Changelog, https://github.com/JacobCoffee/niapi/releases/
Project-URL: Documentation, https://jacobcoffee.github.io/niapi/index.html
Project-URL: Issue Tracker, https://github.com/JacobCoffee/niapi/issues?q=is%3Aissue+is%3Aopen+sort%3Aupdated-desc
Project-URL: Repository, https://github.com/JacobCoffee/niapi
Project-URL: Reddit, https://www.reddit.com/u/monorepo
Project-URL: Twitter, https://twitter.com/_scriptr
